nonebot_plugin_color-0.5.0.post1.dist-info/METADATA
nonebot_plugin_color-0.5.0.post1.dist-info/WHEEL
nonebot_plugin_color-0.5.0.post1.dist-info/entry_points.txt
nonebot_plugin_color-0.5.0.post1.dist-info/licenses/LICENSE
nonebot_plugin_color/__init__.py
nonebot_plugin_color/__main__.py
nonebot_plugin_color/config.py
nonebot_plugin_color/const.py
nonebot_plugin_color/data_source.py
nonebot_plugin_color-0.5.0.post1.dist-info/RECORD
