Metadata-Version: 2.1
Name: nonebot-plugin-color
Version: 0.5.0.post1
Summary: A specified color image generator for Nonebot2
Keywords: nonebot,nonebot2,color
Author-Email: monsterxcn <monsterxcn@gmail.com>, student_2333 <lgc2333@126.com>
License: MIT
Classifier: Programming Language :: Python :: 3
Classifier: License :: OSI Approved :: MIT License
Classifier: Operating System :: OS Independent
Project-URL: homepage, https://github.com/monsterxcn/nonebot-plugin-color
Project-URL: documentation, https://github.com/monsterxcn/nonebot-plugin-color#readme
Project-URL: Bug Tracker, https://github.com/monsterxcn/nonebot-plugin-color/issues
Requires-Python: <4.0,>=3.9
Requires-Dist: nonebot2>=2.3.1
Requires-Dist: nonebot-plugin-alconna>=0.48.0
Requires-Dist: pil-utils>=0.2.1
Provides-Extra: pyd2
Requires-Dist: pydantic-extra-types>=2.8.2; extra == "pyd2"
Provides-Extra: all
Requires-Dist: nonebot-plugin-color[pyd2]; extra == "all"
